google_trans_new_that_works/__init__.py
google_trans_new_that_works/constant.py
google_trans_new_that_works/google_trans_new.py
google_trans_new_that_works-0.1.1.dist-info/LICENSE
google_trans_new_that_works-0.1.1.dist-info/WHEEL
google_trans_new_that_works-0.1.1.dist-info/METADATA
google_trans_new_that_works-0.1.1.dist-info/RECORD
