Metadata-Version: 2.1
Name: google-trans-new-that-works
Version: 0.1.1
Summary: Google translate that works ( i think )
Home-page: https://github.com/AnimeKaizoku/google_trans_new
License: MIT
Author: Sayan Biswas
Author-email: sayan@intellivoid.net
Requires-Python: >=3.7,<4.0
Classifier: License :: OSI Approved :: GNU General Public License v3 (GPLv3)
Classifier: License :: OSI Approved :: MIT License
Classifier: Operating System :: OS Independent
Classifier: Programming Language :: Python :: 3
Classifier: Programming Language :: Python :: 3.10
Classifier: Programming Language :: Python :: 3.7
Classifier: Programming Language :: Python :: 3.8
Classifier: Programming Language :: Python :: 3.9
Requires-Dist: requests (>=2.27.1,<3.0.0)
Requires-Dist: urllib3 (>=1.26.8,<2.0.0)
